YuceFangfaYuShijianZhongwenDierBan/README.md
YuceFangfaYuShijianZhongwenDierBan/__init__.py
YuceFangfaYuShijianZhongwenDierBan/__main__.py
YuceFangfaYuShijianZhongwenDierBan/file.epub
YuceFangfaYuShijianZhongwenDierBan/index.html
YuceFangfaYuShijianZhongwenDierBan/css/__init__.py
YuceFangfaYuShijianZhongwenDierBan/css/annotations.css
YuceFangfaYuShijianZhongwenDierBan/css/main.css
YuceFangfaYuShijianZhongwenDierBan/css/normalize.css
YuceFangfaYuShijianZhongwenDierBan/css/popup.css
YuceFangfaYuShijianZhongwenDierBan/font/__init__.py
YuceFangfaYuShijianZhongwenDierBan/font/fontello.eot
YuceFangfaYuShijianZhongwenDierBan/font/fontello.svg
YuceFangfaYuShijianZhongwenDierBan/font/fontello.ttf
YuceFangfaYuShijianZhongwenDierBan/font/fontello.woff
YuceFangfaYuShijianZhongwenDierBan/img/__init__.py
YuceFangfaYuShijianZhongwenDierBan/img/annotator-glyph-sprite.png
YuceFangfaYuShijianZhongwenDierBan/img/annotator-icon-sprite.png
YuceFangfaYuShijianZhongwenDierBan/img/apple-touch-icon.png
YuceFangfaYuShijianZhongwenDierBan/img/cancelfullscreen.png
YuceFangfaYuShijianZhongwenDierBan/img/close.png
YuceFangfaYuShijianZhongwenDierBan/img/fullscreen.png
YuceFangfaYuShijianZhongwenDierBan/img/loader.gif
YuceFangfaYuShijianZhongwenDierBan/img/menu-icon.png
YuceFangfaYuShijianZhongwenDierBan/img/save.png
YuceFangfaYuShijianZhongwenDierBan/img/saved.png
YuceFangfaYuShijianZhongwenDierBan/img/settings-s.png
YuceFangfaYuShijianZhongwenDierBan/img/settings.png
YuceFangfaYuShijianZhongwenDierBan/img/star.png
YuceFangfaYuShijianZhongwenDierBan/js/__init__.py
YuceFangfaYuShijianZhongwenDierBan/js/epub.js
YuceFangfaYuShijianZhongwenDierBan/js/epub.min.js
YuceFangfaYuShijianZhongwenDierBan/js/epub.min.map
YuceFangfaYuShijianZhongwenDierBan/js/hooks.min.js
YuceFangfaYuShijianZhongwenDierBan/js/hooks.min.map
YuceFangfaYuShijianZhongwenDierBan/js/reader.js
YuceFangfaYuShijianZhongwenDierBan/js/reader.js.map
YuceFangfaYuShijianZhongwenDierBan/js/reader.min.js
yuce_fangfa_yu_shijian_zhongwen_dier_ban-2024.3.5.0.dist-info/METADATA
yuce_fangfa_yu_shijian_zhongwen_dier_ban-2024.3.5.0.dist-info/WHEEL
yuce_fangfa_yu_shijian_zhongwen_dier_ban-2024.3.5.0.dist-info/entry_points.txt
yuce_fangfa_yu_shijian_zhongwen_dier_ban-2024.3.5.0.dist-info/top_level.txt
yuce_fangfa_yu_shijian_zhongwen_dier_ban-2024.3.5.0.dist-info/RECORD
